{
    "configurations": [
        {
            "name": "Linux",
            "includePath": [
                "${workspaceFolder}/**",
                "${workspaceFolder}/lib/**",
                "${workspaceFolder}/lib/sdmsh/lib/libsdm/**",
                "${workspaceFolder}/lib/janusxsdm/**"
            ],
            "defines": [],
            "compilerPath": "/usr/bin/g++",
            "cStandard": "c11",
            "cppStandard": "c++14",
            "intelliSenseMode": "linux-gcc-x64"
        }
    ],
    "version": 4
}